theconcierge/__init__.py
theconcierge/__main__.py
theconcierge/listener/handlers.py
theconcierge/listener/listener.py
theconcierge/main/__init__.py
theconcierge/main/theconcierge.py
theconcierge/settings/__init__.py
theconcierge/settings/config.py
theconcierge-0.0.4.dist-info/LICENSE
theconcierge-0.0.4.dist-info/WHEEL
theconcierge-0.0.4.dist-info/METADATA
theconcierge-0.0.4.dist-info/RECORD
