Metadata-Version: 2.1
Name: theconcierge
Version: 0.0.4
Summary: The Concierge allows you to create a simple project for the development of a ready-to-use Telegram Bot.
Home-page: https://github.com/luigimalaguti/TheConcierge
License: GPLv3
Keywords: theconcierge,telegram,bot,async
Author: luigimalaguti
Author-email: malaguti.luigi@gmail.com
Requires-Python: >=3.7,<4.0
Classifier: Development Status :: 3 - Alpha
Classifier: Intended Audience :: Developers
Classifier: License :: Other/Proprietary License
Classifier: Operating System :: OS Independent
Classifier: Programming Language :: Python :: 3
Classifier: Programming Language :: Python :: 3.7
Classifier: Programming Language :: Python :: 3.8
Classifier: Programming Language :: Python :: 3.9
Requires-Dist: Telethon (>=1.21.1,<2.0.0)
Project-URL: Repository, https://github.com/luigimalaguti/TheConcierge
